databuilder/__init__.py
databuilder/callback/__init__.py
databuilder/callback/call_back.py
databuilder/clients/__init__.py
databuilder/clients/neptune_client.py
databuilder/extractor/__init__.py
databuilder/extractor/athena_metadata_extractor.py
databuilder/extractor/atlas_search_data_extractor.py
databuilder/extractor/base_bigquery_extractor.py
databuilder/extractor/base_extractor.py
databuilder/extractor/base_postgres_metadata_extractor.py
databuilder/extractor/bigquery_metadata_extractor.py
databuilder/extractor/bigquery_usage_extractor.py
databuilder/extractor/bigquery_watermark_extractor.py
databuilder/extractor/cassandra_extractor.py
databuilder/extractor/csv_extractor.py
databuilder/extractor/db2_metadata_extractor.py
databuilder/extractor/db_api_extractor.py
databuilder/extractor/dbt_extractor.py
databuilder/extractor/delta_lake_metadata_extractor.py
databuilder/extractor/dremio_metadata_extractor.py
databuilder/extractor/druid_metadata_extractor.py
databuilder/extractor/es_base_extractor.py
databuilder/extractor/es_column_stats_extractor.py
databuilder/extractor/es_last_updated_extractor.py
databuilder/extractor/es_metadata_extractor.py
databuilder/extractor/feast_extractor.py
databuilder/extractor/generic_extractor.py
databuilder/extractor/generic_usage_extractor.py
databuilder/extractor/glue_extractor.py
databuilder/extractor/hive_table_last_updated_extractor.py
databuilder/extractor/hive_table_metadata_extractor.py
databuilder/extractor/kafka_source_extractor.py
databuilder/extractor/mssql_metadata_extractor.py
databuilder/extractor/mysql_metadata_extractor.py
databuilder/extractor/mysql_search_data_extractor.py
databuilder/extractor/neo4j_extractor.py
databuilder/extractor/neo4j_search_data_extractor.py
databuilder/extractor/neptune_search_data_extractor.py
databuilder/extractor/openlineage_extractor.py
databuilder/extractor/oracle_metadata_extractor.py
databuilder/extractor/pandas_profiling_column_stats_extractor.py
databuilder_amundsen-1.0.0.dist-info/LICENSE
databuilder_amundsen-1.0.0.dist-info/METADATA
databuilder_amundsen-1.0.0.dist-info/NOTICE
databuilder_amundsen-1.0.0.dist-info/WHEEL
databuilder_amundsen-1.0.0.dist-info/top_level.txt
databuilder_amundsen-1.0.0.dist-info/RECORD
