Metadata-Version: 2.1
Name: databuilder-amundsen
Version: 1.0.0
Summary: Amundsen Data builder
Home-page: https://www.github.com/amundsen-io/amundsen/tree/main/databuilder
Maintainer: Tony Chou
Maintainer-email: chonyytony@gmail.com
License: UNKNOWN
Platform: UNKNOWN
Classifier: Programming Language :: Python :: 3.6
Classifier: Programming Language :: Python :: 3.7
Requires-Python: >=3.6
Requires-Dist: elasticsearch (<8.0,>=6.2.0)
Requires-Dist: neo4j-driver (<2.0,>=1.7.2)
Requires-Dist: requests (<3.0,>=2.25.0)
Requires-Dist: freezegun (>=1.1.0)
Requires-Dist: atomicwrites (>=1.1.5)
Requires-Dist: more-itertools (>=4.2.0)
Requires-Dist: pluggy (>=0.6.0)
Requires-Dist: py (>=1.10.0)
Requires-Dist: pyhocon (>=0.3.42)
Requires-Dist: pyparsing (>=2.2.0)
Requires-Dist: sqlalchemy (<1.4,>=1.3.6)
Requires-Dist: wheel (>=0.31.1)
Requires-Dist: neotime (>=1.7.1)
Requires-Dist: pytz (>=2018.4)
Requires-Dist: statsd (>=3.2.1)
Requires-Dist: retrying (>=1.3.3)
Requires-Dist: unicodecsv (<1.0,>=0.14.1)
Requires-Dist: httplib2 (>=0.18.0)
Requires-Dist: unidecode
Requires-Dist: Jinja2 (<4,>=2.10.0)
Requires-Dist: pandas (<1.2.0,>=0.21.0)
Requires-Dist: responses (>=0.10.6)
Requires-Dist: amundsen-common (>=0.16.0)
Requires-Dist: amundsen-rds (==0.0.6)
Provides-Extra: all
Requires-Dist: elasticsearch (<8.0,>=6.2.0) ; extra == 'all'
Requires-Dist: neo4j-driver (<2.0,>=1.7.2) ; extra == 'all'
Requires-Dist: requests (<3.0,>=2.25.0) ; extra == 'all'
Requires-Dist: freezegun (>=1.1.0) ; extra == 'all'
Requires-Dist: atomicwrites (>=1.1.5) ; extra == 'all'
Requires-Dist: more-itertools (>=4.2.0) ; extra == 'all'
Requires-Dist: pluggy (>=0.6.0) ; extra == 'all'
Requires-Dist: py (>=1.10.0) ; extra == 'all'
Requires-Dist: pyhocon (>=0.3.42) ; extra == 'all'
Requires-Dist: pyparsing (>=2.2.0) ; extra == 'all'
Requires-Dist: sqlalchemy (<1.4,>=1.3.6) ; extra == 'all'
Requires-Dist: wheel (>=0.31.1) ; extra == 'all'
Requires-Dist: neotime (>=1.7.1) ; extra == 'all'
Requires-Dist: pytz (>=2018.4) ; extra == 'all'
Requires-Dist: statsd (>=3.2.1) ; extra == 'all'
Requires-Dist: retrying (>=1.3.3) ; extra == 'all'
Requires-Dist: unicodecsv (<1.0,>=0.14.1) ; extra == 'all'
Requires-Dist: httplib2 (>=0.18.0) ; extra == 'all'
Requires-Dist: unidecode ; extra == 'all'
Requires-Dist: Jinja2 (<4,>=2.10.0) ; extra == 'all'
Requires-Dist: pandas (<1.2.0,>=0.21.0) ; extra == 'all'
Requires-Dist: responses (>=0.10.6) ; extra == 'all'
Requires-Dist: amundsen-common (>=0.16.0) ; extra == 'all'
Requires-Dist: amundsen-rds (==0.0.6) ; extra == 'all'
Requires-Dist: flake8 (>=3.9.2) ; extra == 'all'
Requires-Dist: flake8-tidy-imports (>=4.3.0) ; extra == 'all'
Requires-Dist: isort[colors] (~=5.8.0) ; extra == 'all'
Requires-Dist: mock (>=4.0.3) ; extra == 'all'
Requires-Dist: mypy (<0.900,>=0.812) ; extra == 'all'
Requires-Dist: pytest (>=6.2.4) ; extra == 'all'
Requires-Dist: pytest-cov (>=2.12.0) ; extra == 'all'
Requires-Dist: pytest-env (>=0.6.2) ; extra == 'all'
Requires-Dist: pytest-mock (>=3.6.1) ; extra == 'all'
Requires-Dist: typed-ast (>=1.4.3) ; extra == 'all'
Requires-Dist: confluent-kafka (==1.0.0) ; extra == 'all'
Requires-Dist: cassandra-driver (==3.20.1) ; extra == 'all'
Requires-Dist: boto3 (==1.17.23) ; extra == 'all'
Requires-Dist: snowflake-connector-python ; extra == 'all'
Requires-Dist: snowflake-sqlalchemy ; extra == 'all'
Requires-Dist: PyAthena[sqlalchemy] (<2.0.0,>=1.0.0) ; extra == 'all'
Requires-Dist: google-api-python-client (<2.0.0dev,>=1.6.0) ; extra == 'all'
Requires-Dist: google-auth-httplib2 (>=0.0.1) ; extra == 'all'
Requires-Dist: google-auth (<2.0.0dev,>=1.0.0) ; extra == 'all'
Requires-Dist: jsonpath-rw (==1.4.0) ; extra == 'all'
Requires-Dist: ibm-db (==3.0.1) ; extra == 'all'
Requires-Dist: ibm-db-sa-py3 (==0.3.1-1) ; extra == 'all'
Requires-Dist: pyodbc (==4.0.30) ; extra == 'all'
Requires-Dist: pydruid ; extra == 'all'
Requires-Dist: pyspark (==3.0.1) ; extra == 'all'
Requires-Dist: feast (==0.8.0) ; extra == 'all'
Requires-Dist: amundsen-gremlin (>=0.0.9) ; extra == 'all'
Requires-Dist: Flask (==1.0.2) ; extra == 'all'
Requires-Dist: gremlinpython (==3.4.3) ; extra == 'all'
Requires-Dist: requests-aws4auth (==1.1.0) ; extra == 'all'
Requires-Dist: typing-extensions (==3.7.4) ; extra == 'all'
Requires-Dist: overrides (==2.5) ; extra == 'all'
Requires-Dist: mysqlclient (<3,>=1.3.6) ; extra == 'all'
Requires-Dist: pyatlasclient (==1.1.2) ; extra == 'all'
Requires-Dist: apache-atlas (>=0.0.11) ; extra == 'all'
Requires-Dist: simple-salesforce (>=1.11.2) ; extra == 'all'
Requires-Dist: cx-Oracle (==8.2.1) ; extra == 'all'
Provides-Extra: athena
Requires-Dist: PyAthena[sqlalchemy] (<2.0.0,>=1.0.0) ; extra == 'athena'
Provides-Extra: atlas
Requires-Dist: pyatlasclient (==1.1.2) ; extra == 'atlas'
Requires-Dist: apache-atlas (>=0.0.11) ; extra == 'atlas'
Provides-Extra: bigquery
Requires-Dist: google-api-python-client (<2.0.0dev,>=1.6.0) ; extra == 'bigquery'
Requires-Dist: google-auth-httplib2 (>=0.0.1) ; extra == 'bigquery'
Requires-Dist: google-auth (<2.0.0dev,>=1.0.0) ; extra == 'bigquery'
Provides-Extra: cassandra
Requires-Dist: cassandra-driver (==3.20.1) ; extra == 'cassandra'
Provides-Extra: db2
Requires-Dist: ibm-db (==3.0.1) ; extra == 'db2'
Requires-Dist: ibm-db-sa-py3 (==0.3.1-1) ; extra == 'db2'
Provides-Extra: delta
Requires-Dist: pyspark (==3.0.1) ; extra == 'delta'
Provides-Extra: dev
Requires-Dist: flake8 (>=3.9.2) ; extra == 'dev'
Requires-Dist: flake8-tidy-imports (>=4.3.0) ; extra == 'dev'
Requires-Dist: isort[colors] (~=5.8.0) ; extra == 'dev'
Requires-Dist: mock (>=4.0.3) ; extra == 'dev'
Requires-Dist: mypy (<0.900,>=0.812) ; extra == 'dev'
Requires-Dist: pytest (>=6.2.4) ; extra == 'dev'
Requires-Dist: pytest-cov (>=2.12.0) ; extra == 'dev'
Requires-Dist: pytest-env (>=0.6.2) ; extra == 'dev'
Requires-Dist: pytest-mock (>=3.6.1) ; extra == 'dev'
Requires-Dist: typed-ast (>=1.4.3) ; extra == 'dev'
Provides-Extra: dremio
Requires-Dist: pyodbc (==4.0.30) ; extra == 'dremio'
Provides-Extra: druid
Requires-Dist: pydruid ; extra == 'druid'
Provides-Extra: feast
Requires-Dist: feast (==0.8.0) ; extra == 'feast'
Provides-Extra: glue
Requires-Dist: boto3 (==1.17.23) ; extra == 'glue'
Provides-Extra: jsonpath
Requires-Dist: jsonpath-rw (==1.4.0) ; extra == 'jsonpath'
Provides-Extra: kafka
Requires-Dist: confluent-kafka (==1.0.0) ; extra == 'kafka'
Provides-Extra: neptune
Requires-Dist: amundsen-gremlin (>=0.0.9) ; extra == 'neptune'
Requires-Dist: Flask (==1.0.2) ; extra == 'neptune'
Requires-Dist: gremlinpython (==3.4.3) ; extra == 'neptune'
Requires-Dist: requests-aws4auth (==1.1.0) ; extra == 'neptune'
Requires-Dist: typing-extensions (==3.7.4) ; extra == 'neptune'
Requires-Dist: overrides (==2.5) ; extra == 'neptune'
Requires-Dist: boto3 (==1.17.23) ; extra == 'neptune'
Provides-Extra: oracle
Requires-Dist: cx-Oracle (==8.2.1) ; extra == 'oracle'
Provides-Extra: rds
Requires-Dist: sqlalchemy (<1.4,>=1.3.6) ; extra == 'rds'
Requires-Dist: mysqlclient (<3,>=1.3.6) ; extra == 'rds'
Provides-Extra: salesforce
Requires-Dist: simple-salesforce (>=1.11.2) ; extra == 'salesforce'
Provides-Extra: snowflake
Requires-Dist: snowflake-connector-python ; extra == 'snowflake'
Requires-Dist: snowflake-sqlalchemy ; extra == 'snowflake'
